potter_spells/__init__.py
potter_spells/all_by_type.py
potter_spells/all_data.py
potter_spells/all_enchantment_names.py
potter_spells/all_spell_names.py
potter_spells/enchants_by_type.py
potter_spells/find.py
potter_spells/scrape.py
potter_spells/spells_by_type.py
potter_spells-1.0.2.dist-info/LICENSE
potter_spells-1.0.2.dist-info/METADATA
potter_spells-1.0.2.dist-info/WHEEL
potter_spells-1.0.2.dist-info/top_level.txt
potter_spells-1.0.2.dist-info/RECORD
