Metadata-Version: 2.1
Name: potter-spells
Version: 1.0.2
Summary: A python package to list all Harry Potter spells
Home-page: https://github.com/Vibhu-Agarwal/potter_spells
Author: Vibhu Agarwal
Author-email: vibhu4agarwal@gmail.com
License: MIT
Keywords: harry potter harrypotter spells harrypotterspells potterspells expelliarmus
Platform: UNKNOWN
Classifier: Programming Language :: Python :: 3
Classifier: License :: OSI Approved :: MIT License
Classifier: Operating System :: OS Independent
Requires-Dist: beautifulsoup4 (==4.6.3)
Requires-Dist: bs4 (==0.0.1)
Requires-Dist: certifi (==2018.10.15)
Requires-Dist: chardet (==3.0.4)
Requires-Dist: dataclasses (==0.6)
Requires-Dist: idna (==2.7)
Requires-Dist: lxml (==4.2.5)
Requires-Dist: requests (==2.20.1)
Requires-Dist: urllib3 (==1.24.1)
